laydata_core/__init__.py
laydata_core/client.py
laydata_core/client_retry.py
laydata_core/config.py
laydata_core/errors.py
laydata_core/logger.py
laydata_core/metrics.py
laydata_core/recent.py
laydata_core/retry.py
laydata_core/singleflight.py
laydata_core/types.py
laydata_core/utils.py
laydata_core-0.1.0.dist-info/METADATA
laydata_core-0.1.0.dist-info/WHEEL
laydata_core-0.1.0.dist-info/top_level.txt
laydata_core-0.1.0.dist-info/RECORD
