Metadata-Version: 2.4
Name: laydata-core
Version: 0.1.0
Summary: Shared core for Laydata server and client
Requires-Python: >=3.10
Requires-Dist: httpx[http2]>=0.25.0
Requires-Dist: typing-extensions>=4.0.0
Requires-Dist: python-dotenv>=1.0.0
